graphgen/__init__.py
graphgen/graphgen.py
graphgen/networking.py
graphgen/nxgraph.py
diagen-0.0.2.dist-info/LICENSE
diagen-0.0.2.dist-info/METADATA
diagen-0.0.2.dist-info/WHEEL
diagen-0.0.2.dist-info/top_level.txt
diagen-0.0.2.dist-info/RECORD
