Metadata-Version: 2.1
Name: diagen
Version: 0.0.2
Summary: Technical diagram generator with autorouting on top of pydot and networkx
Author-email: Alex Pyattaev <mail@mail.com>
License: GNU GENERAL PUBLIC LICENSE
Project-URL: Homepage, https://github.com/alexpyattaev/diagen
Project-URL: Bug Tracker, https://github.com/alexpyattaev/diagen/issues
Classifier: Programming Language :: Python :: 3
Classifier: License :: OSI Approved :: GNU General Public License v3 (GPLv3)
Classifier: Operating System :: OS Independent
Requires-Python: >=3.10
License-File: LICENSE
Requires-Dist: pydot
Requires-Dist: networkx
Requires-Dist: matplotlib
